tgfeed/__init__.py
tgfeed/__main__.py
tgfeed/config.py
tgfeed/message.py
tgfeed/scheme.py
tgfeed/utils.py
tgfeed/validate.py
tgfeed-0.1.3.dist-info/licenses/LICENSE
tgfeed-0.1.3.dist-info/METADATA
tgfeed-0.1.3.dist-info/WHEEL
tgfeed-0.1.3.dist-info/top_level.txt
tgfeed-0.1.3.dist-info/RECORD
