Metadata-Version: 2.4
Name: tgfeed
Version: 0.1.3
Summary: Create feeds in Telegram easily
Author-email: Nikolai <magnickolas@gmail.com>
Requires-Python: <4.0,>=3.9
License-File: LICENSE
Requires-Dist: Telethon~=1.40.0
Requires-Dist: appdirs<2.0.0,>=1.4.4
Requires-Dist: loguru<0.8.0,>=0.7.3
Requires-Dist: jsonpickle<5.0.0,>=4.1.1
Dynamic: license-file
